iroha_cli/__init__.py
iroha_cli/built_in_commands.py
iroha_cli/commands.py
iroha_cli/completer.py
iroha_cli/crypto.py
iroha_cli/crypto_ed25519.py
iroha_cli/exception.py
iroha_cli/file_io.py
iroha_cli/loader.py
iroha_cli/main.py
iroha_cli/network.py
iroha_cli/query.py
iroha_cli/libs/__init__.py
iroha_cli/libs/amount.py
iroha_ya_cli-2.0.1.dist-info/DESCRIPTION.rst
iroha_ya_cli-2.0.1.dist-info/METADATA
iroha_ya_cli-2.0.1.dist-info/RECORD
iroha_ya_cli-2.0.1.dist-info/WHEEL
iroha_ya_cli-2.0.1.dist-info/entry_points.txt
iroha_ya_cli-2.0.1.dist-info/metadata.json
iroha_ya_cli-2.0.1.dist-info/top_level.txt
tests/__init__.py
tests/test_built_in_command.py
tests/test_cli.py
tests/test_command.py
tests/test_exception.py
tests/test_loader.py
tests/test_network.py
