Metadata-Version: 2.0
Name: iroha-ya-cli
Version: 2.0.1
Summary: Cli for hyperledger/iroha
Home-page: UNKNOWN
Author: Sonoko Mizuki
Author-email: mizuki.sonoko@gmail.com
License: Apache
Platform: UNKNOWN
Classifier: Programming Language :: Python :: 3.5
Classifier: Development Status :: 4 - Beta
Classifier: License :: OSI Approved :: Apache Software License
Classifier: Topic :: Utilities
Requires-Dist: grpcio
Requires-Dist: grpcio-tools
Requires-Dist: protobuf
Requires-Dist: PyYAML
Requires-Dist: ed25519-python
